MANIFEST.in
README.md
setup.py
BuildbotEightStatusShields.egg-info/PKG-INFO
BuildbotEightStatusShields.egg-info/SOURCES.txt
BuildbotEightStatusShields.egg-info/dependency_links.txt
BuildbotEightStatusShields.egg-info/requires.txt
BuildbotEightStatusShields.egg-info/top_level.txt
BuildbotStatusShields/__init__.py
BuildbotStatusShields/shields.py
BuildbotStatusShields/templates/badge.svg.j2
BuildbotStatusShields/templates/flat-square.svg.j2
BuildbotStatusShields/templates/flat.svg.j2
BuildbotStatusShields/templates/plastic.svg.j2