Metadata-Version: 1.1
Name: BuildbotEightStatusShields
Version: 0.1
Summary: Adds shields.io-style badges to Buildbot
Home-page: https://github.com/thefinn93/BuildbotStatusShields
Author: Finn Herzfeld
Author-email: finn@finn.io
License: GPLv2
Keywords: shields badges status Buildbot
Platform: UNKNOWN
Classifier: Development Status :: 3 - Alpha
